syunity_core/__init__.py
syunity_core/settings.py
syunity_core/database/__init__.py
syunity_core/database/iotdb_manager.py
syunity_core/database/sqlite_manager.py
syunity_core/network/__init__.py
syunity_core/network/databus.py
syunity_core/network/handler_registry.py
syunity_core/network/mqttcore.py
syunity_core/security/__init__.py
syunity_core/security/crypto.py
syunity_core/security/jwt_auth.py
syunity_core/security/rbac.py
syunity_core/system/__init__.py
syunity_core/system/logger.py
syunity_core/system/platform_info.py
syunity_core/system/thread_pool.py
syunity_core/utils/__init__.py
syunity_core/utils/date_utils.py
syunity_core/utils/weather.py
syunity_core/web/__init__.py
syunity_core/web/sanic_server.py
syunity_core-0.0.9.dist-info/licenses/LICENSE
syunity_core-0.0.9.dist-info/METADATA
syunity_core-0.0.9.dist-info/WHEEL
syunity_core-0.0.9.dist-info/top_level.txt
syunity_core-0.0.9.dist-info/RECORD
