Metadata-Version: 2.4
Name: syunity-core
Version: 0.0.9
Summary: A unified core kernel containing MQTT (v2), IoTDB, Sanic, and utility modules for Syunity projects.
Author-email: ZHOU HUAN <shenarder@syunity.cn>
License-Expression: MIT
Project-URL: Homepage, https://gitee.com/shenarder/syunity-core
Project-URL: Bug Tracker, https://gitee.com/shenarder/syunity-core/issues
Keywords: iot,mqtt,sanic,iotdb,utility,kernel
Classifier: Development Status :: 3 - Alpha
Classifier: Intended Audience :: Developers
Classifier: Topic :: Software Development :: Libraries :: Python Modules
Classifier: Programming Language :: Python :: 3
Classifier: Programming Language :: Python :: 3.9
Classifier: Programming Language :: Python :: 3.10
Classifier: Programming Language :: Python :: 3.11
Classifier: Programming Language :: Python :: 3.12
Requires-Python: >=3.9
License-File: LICENSE
Requires-Dist: cryptography>=43.0.0
Requires-Dist: PyYAML>=6.0.0
Requires-Dist: loguru>=0.7.0
Requires-Dist: pendulum>=3.0.0
Requires-Dist: psutil>=6.0.0
Requires-Dist: apache-iotdb>=1.3.0
Requires-Dist: deepmerge>=1.1.0
Requires-Dist: numpy>=1.26.0
Requires-Dist: paho-mqtt>=2.1.0
Requires-Dist: pandas>=2.0.0
Requires-Dist: pydantic>=2.0.0
Requires-Dist: pydantic-settings>=2.0.0
Requires-Dist: PyJWT>=2.8.0
Requires-Dist: pypinyin>=0.49.0
Requires-Dist: bcrypt>=4.0.0
Requires-Dist: requests>=2.31.0
Requires-Dist: sanic>=23.12.0
Dynamic: license-file
